nomad_camels_driver_iBeam_smart/__init__.py
nomad_camels_driver_iBeam_smart/iBeam_smart.py
nomad_camels_driver_iBeam_smart/iBeam_smart_ophyd.py
nomad_camels_driver_ibeam_smart-0.1.1.dist-info/LICENSE.txt
nomad_camels_driver_ibeam_smart-0.1.1.dist-info/METADATA
nomad_camels_driver_ibeam_smart-0.1.1.dist-info/WHEEL
nomad_camels_driver_ibeam_smart-0.1.1.dist-info/top_level.txt
nomad_camels_driver_ibeam_smart-0.1.1.dist-info/RECORD
